{
  "arch": "x86_64",
  "build": "ha4b6fd6_2",
  "build_number": 2,
  "depends": [
    "__glibc >=2.17,<3.0.a0",
    "libglvnd 1.7.0 ha4b6fd6_2",
    "libglx 1.7.0 ha4b6fd6_2"
  ],
  "license": "LicenseRef-libglvnd",
  "md5": "928b8be80851f5d8ffb016f9c81dae7a",
  "name": "libgl",
  "platform": "linux",
  "sha256": "dc2752241fa3d9e40ce552c1942d0a4b5eeb93740c9723873f6fcf8d39ef8d2d",
  "size": 134712,
  "subdir": "linux-64",
  "timestamp": 1731330998354,
  "version": "1.7.0",
  "fn": "libgl-1.7.0-ha4b6fd6_2.conda",
  "url": "https://conda.anaconda.org/conda-forge/linux-64/libgl-1.7.0-ha4b6fd6_2.conda",
  "channel": "https://conda.anaconda.org/conda-forge/",
  "extracted_package_dir": "/home/anna/.cache/rattler/cache/pkgs/libgl-1.7.0-ha4b6fd6_2",
  "files": [
    "lib/libGL.so.1",
    "lib/libGL.so.1.7.0"
  ],
  "paths_data": {
    "paths_version": 1,
    "paths": [
      {
        "_path": "lib/libGL.so.1",
        "path_type": "softlink",
        "sha256": "11b5f498cb0f67612e62fbf11ff991849829e5111f04489a58fe8c2f4ebb2744",
        "sha256_in_prefix": "4eb5c70f5cf5926a47d5d36d1cb5aa33d83eb87d7c9b2d96d15ed59969f7adcd",
        "size_in_bytes": 727544
      },
      {
        "_path": "lib/libGL.so.1.7.0",
        "path_type": "hardlink",
        "sha256": "11b5f498cb0f67612e62fbf11ff991849829e5111f04489a58fe8c2f4ebb2744",
        "sha256_in_prefix": "11b5f498cb0f67612e62fbf11ff991849829e5111f04489a58fe8c2f4ebb2744",
        "size_in_bytes": 727544
      }
    ]
  },
  "link": {
    "source": "/home/anna/.cache/rattler/cache/pkgs/libgl-1.7.0-ha4b6fd6_2",
    "type": 1
  }
}